{

    "Mexman" : {
        "lon" : -115.4661,
        "lat" : 31.0292,
        "alt" : 2790,
        "obstime" : "JD",
        "ra"      : "RA",
        "dec"     : "DEC",

        "exptime" : "EXPTIME",
        "binning" : ["CCDXBIN", "CCDYBIN"],
        "gain"    : 3.82,
        "ron"     : 1.8,
        "dark_current" : null,
        "scale"   : 0.264,
        "comment" : ""
    },

    "DFOSC_FASU" : {
        "lon" : "-70:44:14.7926",
        "lat" : "-29:15:27.8194",
        "alt" : 2375,
        "obstime" : "MJD-OBS",
        "ra"      : "RA",
        "dec"     : "DEC",

        "exptime" : "EXPTIME",
        "binning" : null,
        "gain"    : null,
        "ron"     : null,
        "dark_current" : null,
        "scale"   : 0.39,
        "comment" : ""
    },

    "STL-11000 3 CCD Camera" : {
        "lon" : 9.2034,
        "lat" : 44.5911,
        "alt" : 1480,
        "obstime" : "JD",
        "ra"      : null,
        "dec"     : null,

        "exptime" : "EXPTIME",
        "binning" : ["XBINNING", "YBINNING"],
        "gain"    : "EGAIN",
        "ron"     : 11,
        "dark_current" : null,
        "scale"   : 0.22,
        "comment" : ""
    },

    "default": null

}
